{
  "updated": "2026-07-11T06:27:12.046918+00:00",
  "count": 39,
  "stocks": [
    {
      "symbol": "BTC",
      "name": "비트코인",
      "sector": "메이저",
      "price": 64165.93,
      "change": 0.06,
      "volume": 23294013440,
      "turnover": 1494682035810099,
      "marketCap": 1281560,
      "yearHigh": 126198.07,
      "yearLow": 57747.766,
      "pos52": 9,
      "fromHigh": -49.2,
      "nearHigh": false
    },
    {
      "symbol": "ETH",
      "name": "이더리움",
      "sector": "메이저",
      "price": 1798.32,
      "change": 0.15,
      "volume": 7995874304,
      "turnover": 14379140678369,
      "marketCap": 217048,
      "yearHigh": 4953.733,
      "yearLow": 1506.5057,
      "pos52": 8,
      "fromHigh": -63.7,
      "nearHigh": false
    },
    {
      "symbol": "BNB",
      "name": "BNB",
      "sector": "거래소",
      "price": 575.44,
      "change": 0.07,
      "volume": 1007756352,
      "turnover": 579903315195,
      "marketCap": 79258,
      "yearHigh": 1370.546,
      "yearLow": 538.59924,
      "pos52": 4,
      "fromHigh": -58.0,
      "nearHigh": false
    },
    {
      "symbol": "T",
      "name": "테더",
      "sector": "스테이블",
      "price": 0.99911,
      "change": -0.02,
      "volume": 51742318592,
      "turnover": 51696267928,
      "marketCap": 186928,
      "yearHigh": 1.00751,
      "yearLow": 0.98958,
      "pos52": 53,
      "fromHigh": -0.8,
      "nearHigh": false
    },
    {
      "symbol": "BCH",
      "name": "비트코인캐시",
      "sector": "결제",
      "price": 244.84,
      "change": -0.15,
      "volume": 139722736,
      "turnover": 34209714682,
      "marketCap": 4891,
      "yearHigh": 668.0633,
      "yearLow": 181.24191,
      "pos52": 13,
      "fromHigh": -63.4,
      "nearHigh": false
    },
    {
      "symbol": "AAVE",
      "name": "에이브",
      "sector": "디파이",
      "price": 95.2,
      "change": -0.57,
      "volume": 276950688,
      "turnover": 26365705498,
      "marketCap": 1445,
      "yearHigh": 382.93417,
      "yearLow": 58.04708,
      "pos52": 11,
      "fromHigh": -75.1,
      "nearHigh": false
    },
    {
      "symbol": "XMR",
      "name": "모네로",
      "sector": "프라이버시",
      "price": 323.32,
      "change": 0.39,
      "volume": 75711272,
      "turnover": 24478968463,
      "marketCap": 5964,
      "yearHigh": 798.91486,
      "yearLow": 233.09096,
      "pos52": 16,
      "fromHigh": -59.5,
      "nearHigh": false
    },
    {
      "symbol": "C",
      "name": "USD코인",
      "sector": "스테이블",
      "price": 0.9997,
      "change": -0.01,
      "volume": 9436779520,
      "turnover": 9433948486,
      "marketCap": 75591,
      "yearHigh": 1.00496,
      "yearLow": 0.99667,
      "pos52": 37,
      "fromHigh": -0.5,
      "nearHigh": false
    },
    {
      "symbol": "LTC",
      "name": "라이트코인",
      "sector": "결제",
      "price": 45.01,
      "change": 0.58,
      "volume": 178236288,
      "turnover": 8022415323,
      "marketCap": 3453,
      "yearHigh": 135.56294,
      "yearLow": 39.38718,
      "pos52": 6,
      "fromHigh": -66.8,
      "nearHigh": false
    },
    {
      "symbol": "LINK",
      "name": "체인링크",
      "sector": "오라클",
      "price": 7.99,
      "change": 0.37,
      "volume": 198227504,
      "turnover": 1584234212,
      "marketCap": 5659,
      "yearHigh": 27.73526,
      "yearLow": 7.0224,
      "pos52": 5,
      "fromHigh": -71.2,
      "nearHigh": false
    },
    {
      "symbol": "AVAX",
      "name": "아발란체",
      "sector": "레이어1",
      "price": 6.71,
      "change": -0.4,
      "volume": 177422512,
      "turnover": 1190505056,
      "marketCap": 2887,
      "yearHigh": 35.91024,
      "yearLow": 5.69357,
      "pos52": 3,
      "fromHigh": -81.3,
      "nearHigh": false
    },
    {
      "symbol": "XRP",
      "name": "리플",
      "sector": "결제",
      "price": 1.11,
      "change": 0.24,
      "volume": 998453824,
      "turnover": 1104789156,
      "marketCap": 67138,
      "yearHigh": 3.65021,
      "yearLow": 1.00975,
      "pos52": 4,
      "fromHigh": -69.7,
      "nearHigh": false
    },
    {
      "symbol": "UNI",
      "name": "유니스왑",
      "sector": "디파이",
      "price": 3.52,
      "change": -0.16,
      "volume": 220538384,
      "turnover": 776295112,
      "marketCap": 2234,
      "yearHigh": 12.25634,
      "yearLow": 2.32774,
      "pos52": 12,
      "fromHigh": -71.3,
      "nearHigh": false
    },
    {
      "symbol": "SOL",
      "name": "솔라나",
      "sector": "레이어1",
      "price": 77.86,
      "change": -0.26,
      "volume": 8294641,
      "turnover": 645820748,
      "marketCap": 43924,
      "yearHigh": 253.2099,
      "yearLow": 60.41472,
      "pos52": 9,
      "fromHigh": -69.3,
      "nearHigh": false
    },
    {
      "symbol": "NEAR",
      "name": "니어프로토콜",
      "sector": "레이어1",
      "price": 1.91,
      "change": 0.82,
      "volume": 147077840,
      "turnover": 280477441,
      "marketCap": 2450,
      "yearHigh": 3.33388,
      "yearLow": 0.86454,
      "pos52": 42,
      "fromHigh": -42.8,
      "nearHigh": false
    },
    {
      "symbol": "ETC",
      "name": "이더리움클래식",
      "sector": "레이어1",
      "price": 7.11,
      "change": 0.64,
      "volume": 30642046,
      "turnover": 217864947,
      "marketCap": 1102,
      "yearHigh": 25.68225,
      "yearLow": 6.45958,
      "pos52": 3,
      "fromHigh": -72.3,
      "nearHigh": false
    },
    {
      "symbol": "TRX",
      "name": "트론",
      "sector": "레이어1",
      "price": 0.3296,
      "change": -0.19,
      "volume": 425006880,
      "turnover": 140082268,
      "marketCap": 31213,
      "yearHigh": 0.37633,
      "yearLow": 0.26814,
      "pos52": 57,
      "fromHigh": -12.4,
      "nearHigh": false
    },
    {
      "symbol": "DOT",
      "name": "폴카닷",
      "sector": "레이어1",
      "price": 0.876,
      "change": -0.04,
      "volume": 122026648,
      "turnover": 106895344,
      "marketCap": 1448,
      "yearHigh": 4.87424,
      "yearLow": 0.79883,
      "pos52": 2,
      "fromHigh": -82.0,
      "nearHigh": false
    },
    {
      "symbol": "ICP",
      "name": "인터넷컴퓨터",
      "sector": "레이어1",
      "price": 2.29,
      "change": -0.63,
      "volume": 46522348,
      "turnover": 106303565,
      "marketCap": 1248,
      "yearHigh": 9.74224,
      "yearLow": 1.97725,
      "pos52": 4,
      "fromHigh": -76.5,
      "nearHigh": false
    },
    {
      "symbol": "ADA",
      "name": "카르다노",
      "sector": "레이어1",
      "price": 0.1671,
      "change": 0.35,
      "volume": 274030400,
      "turnover": 45790480,
      "marketCap": 6007,
      "yearHigh": 1.01646,
      "yearLow": 0.1387,
      "pos52": 3,
      "fromHigh": -83.6,
      "nearHigh": false
    },
    {
      "symbol": "FIL",
      "name": "파일코인",
      "sector": "스토리지",
      "price": 0.789,
      "change": 0.16,
      "volume": 57995352,
      "turnover": 45758333,
      "marketCap": 579,
      "yearHigh": 3.88334,
      "yearLow": 0.63361,
      "pos52": 5,
      "fromHigh": -79.7,
      "nearHigh": false
    },
    {
      "symbol": "DOGE",
      "name": "도지코인",
      "sector": "밈",
      "price": 0.07445,
      "change": 0.55,
      "volume": 445517376,
      "turnover": 33168769,
      "marketCap": 12524,
      "yearHigh": 0.30564,
      "yearLow": 0.069611,
      "pos52": 2,
      "fromHigh": -75.6,
      "nearHigh": false
    },
    {
      "symbol": "XLM",
      "name": "스텔라루멘",
      "sector": "결제",
      "price": 0.19077,
      "change": 0.12,
      "volume": 170126896,
      "turnover": 32455108,
      "marketCap": 6183,
      "yearHigh": 0.51937,
      "yearLow": 0.138,
      "pos52": 14,
      "fromHigh": -63.3,
      "nearHigh": false
    },
    {
      "symbol": "ATOM",
      "name": "코스모스",
      "sector": "레이어1",
      "price": 1.59,
      "change": 0.22,
      "volume": 19938760,
      "turnover": 31702628,
      "marketCap": 774,
      "yearHigh": 5.31565,
      "yearLow": 1.49197,
      "pos52": 3,
      "fromHigh": -70.1,
      "nearHigh": false
    },
    {
      "symbol": "APT",
      "name": "앱토스",
      "sector": "레이어1",
      "price": 0.629,
      "change": -0.04,
      "volume": 42909596,
      "turnover": 26990136,
      "marketCap": 473,
      "yearHigh": 5.64009,
      "yearLow": 0.55473,
      "pos52": 1,
      "fromHigh": -88.8,
      "nearHigh": false
    },
    {
      "symbol": "ARB",
      "name": "아비트럼",
      "sector": "레이어2",
      "price": 0.0905,
      "change": -2.43,
      "volume": 153386288,
      "turnover": 13881459,
      "marketCap": 518,
      "yearHigh": 0.62164,
      "yearLow": 0.070667,
      "pos52": 4,
      "fromHigh": -85.4,
      "nearHigh": false
    },
    {
      "symbol": "AXS",
      "name": "엑시인피니티",
      "sector": "게임",
      "price": 1.01,
      "change": 0.79,
      "volume": 11780723,
      "turnover": 11933872,
      "marketCap": 170,
      "yearHigh": 2.96666,
      "yearLow": 0.79077,
      "pos52": 10,
      "fromHigh": -65.9,
      "nearHigh": false
    },
    {
      "symbol": "HBAR",
      "name": "헤데라",
      "sector": "레이어1",
      "price": 0.07043,
      "change": 0.21,
      "volume": 58142500,
      "turnover": 4094976,
      "marketCap": 3014,
      "yearHigh": 0.30462,
      "yearLow": 0.068524,
      "pos52": 1,
      "fromHigh": -76.9,
      "nearHigh": false
    },
    {
      "symbol": "OP",
      "name": "옵티미즘",
      "sector": "레이어2",
      "price": 0.10446,
      "change": 1.05,
      "volume": 36172868,
      "turnover": 3778618,
      "marketCap": 203,
      "yearHigh": 0.88119,
      "yearLow": 0.088829,
      "pos52": 2,
      "fromHigh": -88.1,
      "nearHigh": false
    },
    {
      "symbol": "MATIC",
      "name": "폴리곤",
      "sector": "레이어2",
      "price": 0.2826,
      "change": 3.51,
      "volume": 12639563,
      "turnover": 3571941,
      "marketCap": 523,
      "yearHigh": 1.28718,
      "yearLow": 0.25035,
      "pos52": 3,
      "fromHigh": -78.0,
      "nearHigh": false
    },
    {
      "symbol": "ALGO",
      "name": "알고랜드",
      "sector": "레이어1",
      "price": 0.0863,
      "change": 0.79,
      "volume": 21727194,
      "turnover": 1875057,
      "marketCap": 763,
      "yearHigh": 0.33481,
      "yearLow": 0.08,
      "pos52": 2,
      "fromHigh": -74.2,
      "nearHigh": false
    },
    {
      "symbol": "THETA",
      "name": "쎄타",
      "sector": "미디어",
      "price": 0.14789,
      "change": 6.86,
      "volume": 10572108,
      "turnover": 1563509,
      "marketCap": 148,
      "yearHigh": 1.00962,
      "yearLow": 0.12334,
      "pos52": 3,
      "fromHigh": -85.4,
      "nearHigh": false
    },
    {
      "symbol": "SAND",
      "name": "샌드박스",
      "sector": "메타버스",
      "price": 0.0499,
      "change": 1.14,
      "volume": 13831924,
      "turnover": 690213,
      "marketCap": 133,
      "yearHigh": 0.35656,
      "yearLow": 0.045073,
      "pos52": 2,
      "fromHigh": -86.0,
      "nearHigh": false
    },
    {
      "symbol": "FTM",
      "name": "팬텀",
      "sector": "레이어1",
      "price": 0.02681,
      "change": 3.11,
      "volume": 10850732,
      "turnover": 290908,
      "marketCap": 77,
      "yearHigh": 0.41771,
      "yearLow": 0.019153,
      "pos52": 2,
      "fromHigh": -93.6,
      "nearHigh": false
    },
    {
      "symbol": "GRT",
      "name": "더그래프",
      "sector": "디파이",
      "price": 0.017697,
      "change": 0.27,
      "volume": 11446279,
      "turnover": 202563,
      "marketCap": 189,
      "yearHigh": 0.12045,
      "yearLow": 0.017242,
      "pos52": 0,
      "fromHigh": -85.3,
      "nearHigh": false
    },
    {
      "symbol": "FLOW",
      "name": "플로우",
      "sector": "레이어1",
      "price": 0.02707,
      "change": -0.32,
      "volume": 3124861,
      "turnover": 84590,
      "marketCap": 44,
      "yearHigh": 0.45842,
      "yearLow": 0.024551,
      "pos52": 1,
      "fromHigh": -94.1,
      "nearHigh": false
    },
    {
      "symbol": "VET",
      "name": "비체인",
      "sector": "레이어1",
      "price": 0.004827,
      "change": 1.34,
      "volume": 10996802,
      "turnover": 53083,
      "marketCap": 415,
      "yearHigh": 0.029518,
      "yearLow": 0.004281,
      "pos52": 2,
      "fromHigh": -83.6,
      "nearHigh": false
    },
    {
      "symbol": "EOS",
      "name": "이오스",
      "sector": "레이어1",
      "price": 0.077157,
      "change": -1.96,
      "volume": 37419,
      "turnover": 2887,
      "marketCap": 117,
      "yearHigh": 0.64436,
      "yearLow": 0.055195,
      "pos52": 4,
      "fromHigh": -88.0,
      "nearHigh": false
    },
    {
      "symbol": "SHIB",
      "name": "시바이누",
      "sector": "밈",
      "price": 4e-06,
      "change": 0.17,
      "volume": 49311504,
      "turnover": 217,
      "marketCap": 2593,
      "yearHigh": 1.6e-05,
      "yearLow": 4e-06,
      "pos52": 3,
      "fromHigh": -72.5,
      "nearHigh": false
    }
  ]
}